bigrange.py
dlog.py
ec.py
ent.py
test_ec.py
ECCArithmetic-1.0.0.dist-info/LICENSE
ECCArithmetic-1.0.0.dist-info/METADATA
ECCArithmetic-1.0.0.dist-info/WHEEL
ECCArithmetic-1.0.0.dist-info/top_level.txt
ECCArithmetic-1.0.0.dist-info/RECORD
