Metadata-Version: 2.1
Name: ECCArithmetic
Version: 1.0.0
Summary: Python Elliptic Curve Arithmetic Library.
Home-page: UNKNOWN
Author: Parthkumar Rathod, Rakshit Joshi, Mahesh Hegde
Author-email: parthcrathod@gmail.com, rakshitjoshi211997@gmail.com, maheshhegde113@gmail.com
License: UNKNOWN
Platform: UNKNOWN
Classifier: Programming Language :: Python :: 3
Classifier: License :: OSI Approved :: MIT License
Classifier: Operating System :: OS Independent
Classifier: Intended Audience :: Developers
Classifier: Intended Audience :: Education
Classifier: Topic :: Security :: Cryptography
Requires-Python: >=3.0
